geop4th/__init__.py
geop4th/geobricks.py
geop4th/download/__init__.py
geop4th/download/download_fr.py
geop4th/download/download_wl.py
geop4th/graphics/SIM2_tools.py
geop4th/graphics/__init__.py
geop4th/graphics/cmapgenerator.py
geop4th/graphics/monitor_memory.py
geop4th/graphics/ncplot.py
geop4th/graphics/trajplot.py
geop4th/graphics/visualization_advanced.py
geop4th/misc/cwatm/plot_timeseries.py
geop4th/misc/cwatm/readsettings.py
geop4th/workflows/__init__.py
geop4th/workflows/format/__init__.py
geop4th/workflows/format/cwatm.py
geop4th/workflows/standardize/ERA5_preprocessing_pipeline.py
geop4th/workflows/standardize/__init__.py
geop4th/workflows/standardize/standardize_fr.py
geop4th/workflows/standardize/ERA5/era5_sommaire.py
geop4th/workflows/standardize/ERA5/geohydroconvert.py
geop4th-0.11.1.dist-info/licenses/COPYING
geop4th-0.11.1.dist-info/METADATA
geop4th-0.11.1.dist-info/WHEEL
geop4th-0.11.1.dist-info/top_level.txt
geop4th-0.11.1.dist-info/RECORD
