Metadata-Version: 2.4
Name: geop4th
Version: 0.11.1
Summary: GEOP4TH (for GEOspatial Python Pre-Processing Platform for Trajectories in Hydro-socio-ecosystems) is a collection of generic, format-agnostic, python tools (geobricks) designed to easily standardize, manipulate and visualize space-time data.
Author-email: Alexandre Kenshilik Coche <alexandre.co@hotmail.fr>, Bastien Boivin <bastien.boivin@univ-rennes.fr>
License: GNU GENERAL PUBLIC LICENSE
Project-URL: homepage, https://gitlab.com/AlexandreCoche/geop4th
Project-URL: documentation, https://AlexandreCoche.gitlab.io/geop4th
Project-URL: docker, https://hub.docker.com/r/alexandrecoche/geop4th
Keywords: dataset pre-processing,data visualization,FAIR,collaborative,toolbox,Python 3,Climate Change,Geography,Hydrology,GIS
Classifier: Programming Language :: Python :: 3
Classifier: License :: OSI Approved :: GNU General Public License v3 (GPLv3)
Classifier: Operating System :: OS Independent
Classifier: Intended Audience :: Science/Research
Classifier: Topic :: Scientific/Engineering :: GIS
Requires-Python: >=3.11
License-File: COPYING
Requires-Dist: numpy>1.0.0
Requires-Dist: setuptools>=67
Requires-Dist: rioxarray>=0.10.0
Requires-Dist: pandas>1.0.0
Requires-Dist: geopandas>0.10
Requires-Dist: xarray
Requires-Dist: netCDF4
Requires-Dist: h5netcdf
Requires-Dist: rasterio<2.0,>=1.0
Requires-Dist: shapely>=1.8
Requires-Dist: affine<3.0,>=2.3
Requires-Dist: fiona<2.0,>=1.8
Requires-Dist: pysheds>=0.5
Requires-Dist: matplotlib
Requires-Dist: plotly
Requires-Dist: Pillow<12.0,>=11.0
Requires-Dist: kaleido
Provides-Extra: test
Requires-Dist: pytest; extra == "test"
Requires-Dist: pytest-cov; extra == "test"
Requires-Dist: packaging; extra == "test"
Provides-Extra: docs
Requires-Dist: sphinx; extra == "docs"
Requires-Dist: numpydoc; extra == "docs"
Requires-Dist: sphinx-rtd-theme; extra == "docs"
Requires-Dist: pydata-sphinx-theme; extra == "docs"
Requires-Dist: sphinx-multiversion; extra == "docs"
Requires-Dist: sphinx-tabs; extra == "docs"
Requires-Dist: sphinx-design; extra == "docs"
Requires-Dist: sphinx-copybutton; extra == "docs"
Requires-Dist: sphinx-togglebutton; extra == "docs"
Dynamic: license-file
